hum_catcher/__init__.py
hum_catcher/__main__.py
hum_catcher/analysis.py
hum_catcher/csv_utils.py
hum_catcher/match.py
hum_catcher/types.py
hum_catcher/ui.py
hum_catcher-0.1.1.dist-info/licenses/LICENSE
hum_catcher-0.1.1.dist-info/METADATA
hum_catcher-0.1.1.dist-info/WHEEL
hum_catcher-0.1.1.dist-info/entry_points.txt
hum_catcher-0.1.1.dist-info/top_level.txt
hum_catcher-0.1.1.dist-info/RECORD
