Metadata-Version: 2.4
Name: hum-catcher
Version: 0.1.1
Summary: Electrical Network Frequency (ENF) analysis and matching tool.
Author-email: schello24r <schello24r@gmail.com>
License: MIT License
Project-URL: Repository, https://github.com/sch24r/hum-catcher
Project-URL: Bug Tracker, https://github.com/sch24r/hum-catcher/issues
Keywords: audio,enf,forensics,grid frequency,mains hum
Classifier: Programming Language :: Python :: 3
Classifier: License :: OSI Approved :: MIT License
Classifier: Operating System :: OS Independent
Classifier: Topic :: Multimedia :: Sound/Audio :: Analysis
Classifier: Topic :: Scientific/Engineering :: Information Analysis
Requires-Python: >=3.8
License-File: LICENSE
Requires-Dist: numpy
Requires-Dist: scipy
Requires-Dist: matplotlib
Requires-Dist: audiofile
Requires-Dist: sortedcontainers
Requires-Dist: tqdm
Requires-Dist: ffmpeg-python
Requires-Dist: python-dateutil
Provides-Extra: opencl
Requires-Dist: pyopencl; extra == "opencl"
Dynamic: license-file
